SinaTools-1.0.8.data/data/sinatools/environment.yml
sinatools/VERSION
sinatools/__init__.py
sinatools/environment.yml
sinatools/install_env.py
sinatools/sinatools.py
sinatools/CLI/DataDownload/download_files.py
sinatools/CLI/morphology/ALMA_multi_word.py
sinatools/CLI/morphology/morph_analyzer.py
sinatools/CLI/ner/corpus_entity_extractor.py
sinatools/CLI/ner/entity_extractor.py
sinatools/CLI/utils/__init__.py
sinatools/CLI/utils/arStrip.py
sinatools/CLI/utils/corpus_tokenizer.py
sinatools/CLI/utils/implication.py
sinatools/CLI/utils/jaccard.py
sinatools/CLI/utils/remove_latin.py
sinatools/CLI/utils/remove_punctuation.py
sinatools/CLI/utils/sentence_tokenizer.py
sinatools/CLI/utils/text_dublication_detector.py
sinatools/CLI/utils/text_transliteration.py
sinatools/DataDownload/__init__.py
sinatools/DataDownload/downloader.py
sinatools/arabert/__init__.py
sinatools/arabert/preprocess.py
sinatools/arabert/arabert/__init__.py
sinatools/arabert/arabert/create_classification_data.py
sinatools/arabert/arabert/create_pretraining_data.py
sinatools/arabert/arabert/extract_features.py
sinatools/arabert/arabert/lamb_optimizer.py
sinatools/arabert/arabert/modeling.py
sinatools/arabert/arabert/optimization.py
sinatools/arabert/arabert/run_classifier.py
sinatools/arabert/arabert/run_pretraining.py
sinatools/arabert/arabert/run_squad.py
sinatools/arabert/arabert/tokenization.py
sinatools/arabert/araelectra/__init__.py
sinatools/arabert/araelectra/build_openwebtext_pretraining_dataset.py
sinatools/arabert/araelectra/build_pretraining_dataset.py
sinatools/arabert/araelectra/build_pretraining_dataset_single_file.py
sinatools/arabert/araelectra/configure_finetuning.py
sinatools/arabert/araelectra/configure_pretraining.py
sinatools/arabert/araelectra/flops_computation.py
sinatools/arabert/araelectra/run_finetuning.py
sinatools/arabert/araelectra/run_pretraining.py
sinatools/arabert/araelectra/finetune/__init__.py
sinatools/arabert/araelectra/finetune/feature_spec.py
SinaTools-1.0.8.dist-info/AUTHORS.rst
SinaTools-1.0.8.dist-info/LICENSE
SinaTools-1.0.8.dist-info/METADATA
SinaTools-1.0.8.dist-info/WHEEL
SinaTools-1.0.8.dist-info/entry_points.txt
SinaTools-1.0.8.dist-info/top_level.txt
SinaTools-1.0.8.dist-info/RECORD
