Metadata-Version: 2.1
Name: SinaTools
Version: 1.0.8
Summary: Open-source Python toolkit for Arabic Natural Understanding, allowing people to integrate it in their system workflow.
Home-page: https://github.com/SinaLab/sinatools
License: MIT license
Keywords: sinatools
Platform: UNKNOWN
Requires-Dist: six
Requires-Dist: farasapy
Requires-Dist: tqdm
Requires-Dist: requests
Requires-Dist: pathlib
Requires-Dist: transformers (==4.47.1)
Requires-Dist: torchvision (==0.20.1)
Requires-Dist: seqeval (==1.2.2)
Requires-Dist: natsort (==7.1.1)
Requires-Dist: pandas
